pypackt/__init__.py
pypackt/run.py
pypackt/settings.py
pypackt/spider.py
pypackt/user.ini
pypackt/utils.py
pypackt-1.0.1.dist-info/DESCRIPTION.rst
pypackt-1.0.1.dist-info/METADATA
pypackt-1.0.1.dist-info/RECORD
pypackt-1.0.1.dist-info/WHEEL
pypackt-1.0.1.dist-info/entry_points.txt
pypackt-1.0.1.dist-info/metadata.json
pypackt-1.0.1.dist-info/top_level.txt
