Metadata-Version: 2.0
Name: pypackt
Version: 1.0.1
Summary: Tool to claim your daily free eBooks at www.packtpub.com with ease.
Home-page: https://bitbucket.org/kchomski/pypackt
Author: Krzysztof Chomski
Author-email: krzysztof.chomski@gmail.com
License: MIT
Keywords: ebooks,learning,education
Platform: UNKNOWN
Classifier: Development Status :: 5 - Production/Stable
Classifier: Environment :: Console
Classifier: Intended Audience :: Developers
Classifier: Intended Audience :: Education
Classifier: License :: OSI Approved :: MIT License
Classifier: Operating System :: POSIX :: Linux
Classifier: Operating System :: Microsoft :: Windows
Classifier: Programming Language :: Python :: 2.7
Classifier: Programming Language :: Python :: 3
Classifier: Topic :: Education
Requires-Dist: python-crontab
Requires-Dist: requests
Requires-Dist: scrapy
